{
    "transformer": {
        "instanovo-v1.1.0": {
            "remote": "https://github.com/instadeepai/InstaNovo/releases/download/1.0.0/instanovo_extended.ckpt",
            "size": 1136429659
        },
        "instanovo-v1.0.0": {
            "remote": "https://github.com/instadeepai/InstaNovo/releases/download/1.0.0/instanovo_extended.ckpt",
            "size": 1136429659
        }
    },
    "diffusion": {
        "instanovo-plus-v1.1.0": {
            "local": "./checkpoints/diffusion/epoch_2_step_999999"
        }
    }
}
